ttx/__init__.py
ttx/_version.py
ttx/cli.py
ttx/config.py
ttx/db.py
ttx/errors.py
ttx/tasks.py
ttx/time_entries.py
ttx/timeparse.py
ttx/tui.py
ttx_cli-1.2.0.dist-info/METADATA
ttx_cli-1.2.0.dist-info/WHEEL
ttx_cli-1.2.0.dist-info/entry_points.txt
ttx_cli-1.2.0.dist-info/licenses/LICENSE
ttx_cli-1.2.0.dist-info/RECORD
