Metadata-Version: 2.4
Name: ttx-cli
Version: 1.2.0
Summary: Tiny tasks and time tracker
Author-email: Martin Dahl <martindahl16@icloud.com>
License: MIT
License-File: LICENSE
Requires-Python: >=3.8
Requires-Dist: click>=8.0
Requires-Dist: pyyaml>=6.0
Requires-Dist: rich>=13.0.0
Requires-Dist: textual>=0.58.0
Requires-Dist: typer>=0.9.0
Provides-Extra: dev
Requires-Dist: pyright; extra == 'dev'
Requires-Dist: pytest; extra == 'dev'
Requires-Dist: python-semantic-release; extra == 'dev'
Requires-Dist: ruff; extra == 'dev'
Requires-Dist: textual-dev; extra == 'dev'
